evoloop/__init__.py
evoloop/storage.py
evoloop/tracker.py
evoloop/types.py
evoloop/utils.py
evoloop-0.2.1.dist-info/METADATA
evoloop-0.2.1.dist-info/WHEEL
evoloop-0.2.1.dist-info/entry_points.txt
evoloop-0.2.1.dist-info/licenses/LICENSE
evoloop-0.2.1.dist-info/RECORD
