Metadata-Version: 2.4
Name: evoloop
Version: 0.2.1
Summary: A framework-agnostic library for evaluating and improving AI agents
Project-URL: Homepage, https://github.com/tostechbr/evoloop
Project-URL: Documentation, https://github.com/tostechbr/evoloop#readme
Project-URL: Repository, https://github.com/tostechbr/evoloop
Author: EvoLoop Team
License-Expression: MIT
License-File: LICENSE
Keywords: agents,ai,evaluation,langchain,langgraph,llm,self-evolving
Classifier: Development Status :: 3 - Alpha
Classifier: Intended Audience :: Developers
Classifier: License :: OSI Approved :: MIT License
Classifier: Programming Language :: Python :: 3
Classifier: Programming Language :: Python :: 3.10
Classifier: Programming Language :: Python :: 3.11
Classifier: Programming Language :: Python :: 3.12
Classifier: Topic :: Scientific/Engineering :: Artificial Intelligence
Requires-Python: >=3.10
Provides-Extra: all
Requires-Dist: litellm>=1.0.0; extra == 'all'
Requires-Dist: mypy>=1.0.0; extra == 'all'
Requires-Dist: pytest-asyncio>=0.21.0; extra == 'all'
Requires-Dist: pytest>=7.0.0; extra == 'all'
Requires-Dist: rich>=13.0.0; extra == 'all'
Requires-Dist: ruff>=0.1.0; extra == 'all'
Provides-Extra: dev
Requires-Dist: mypy>=1.0.0; extra == 'dev'
Requires-Dist: pytest-asyncio>=0.21.0; extra == 'dev'
Requires-Dist: pytest>=7.0.0; extra == 'dev'
Requires-Dist: ruff>=0.1.0; extra == 'dev'
Provides-Extra: llm
Requires-Dist: litellm>=1.0.0; extra == 'llm'
Provides-Extra: rich
Requires-Dist: rich>=13.0.0; extra == 'rich'
